deepmol_models/__init__.py
deepmol_models/_utils.py
deepmol_models/bokeh_graph.py
deepmol_models/evaluation.py
deepmol_models/models/__init__.py
deepmol_models/models/mixed.py
deepmol_models/models/model.py
deepmol_models/models/np_classifier.py
deepmol_models/models/plants_sm_predictor.py
deepmol_models/models/prediction.py
deepmol_models/models/tdc_models.py
deepmol_models/models/np_classifier/char2idx_class_V1.pkl
deepmol_models/models/np_classifier/char2idx_path_V1.pkl
deepmol_models/models/np_classifier/char2idx_super_V1.pkl
deepmol_models/objectives/__init__.py
deepmol_models/objectives/tdc_objective.py
deepmol_models/pipelines/__init__.py
deepmol_models/pipelines/general_tdc_pipeline.py
deepmol_models/utils/__init__.py
deepmol_models/utils/tdc_benchmark_groups.py
deepmol_models-0.0.5.dist-info/LICENSE
deepmol_models-0.0.5.dist-info/METADATA
deepmol_models-0.0.5.dist-info/WHEEL
deepmol_models-0.0.5.dist-info/top_level.txt
deepmol_models-0.0.5.dist-info/RECORD
